py_netgames_model/messaging/__init__.py
py_netgames_model/messaging/deserializer.py
py_netgames_model/messaging/message.py
py_netgames_model/messaging/webhook_payload.py
py_netgames_model-0.0.1.dist-info/LICENSE.txt
py_netgames_model-0.0.1.dist-info/METADATA
py_netgames_model-0.0.1.dist-info/WHEEL
py_netgames_model-0.0.1.dist-info/top_level.txt
py_netgames_model-0.0.1.dist-info/RECORD
