Metadata-Version: 2.1
Name: py-netgames-model
Version: 0.0.1
Summary: Py-NetGames Internal Model package. Shared between server and client implementations.
Author-email: Gabriel Machado da Roza <gabrielmachadodaroza@outlook.com>
License: MIT License        
License-File: LICENSE.txt
Requires-Dist: dataclasses-json
